except_catcher/__init__.py
except_catcher/admin.py
except_catcher/apps.py
except_catcher/handlers.py
except_catcher/models.py
except_catcher/tests.py
except_catcher/urls.py
except_catcher/views.py
except_catcher/migrations/0001_initial.py
except_catcher/migrations/0002_auto_20180911_1936.py
except_catcher/migrations/__init__.py
except_catcher/static/except_catcher/logo.png
except_catcher/static/except_catcher/style.css
except_catcher/templates/except_catcher/base.html
except_catcher/templates/except_catcher/list_report.html
except_catcher/templates/except_catcher/list_report_header.html
except_catcher/templates/except_catcher/report_list.html
except_catcher/templates/except_catcher/view_error.html
except_catcher/templates/except_catcher/view_error_header.html
except_catcher/templatetags/__init__.py
except_catcher/templatetags/ecatcher.py
django_except_catcher-1.0.0.dist-info/LICENSE
django_except_catcher-1.0.0.dist-info/METADATA
django_except_catcher-1.0.0.dist-info/WHEEL
django_except_catcher-1.0.0.dist-info/top_level.txt
django_except_catcher-1.0.0.dist-info/RECORD
