Metadata-Version: 2.1
Name: django-except-catcher
Version: 1.0.0
Summary: Catch Exceptions in production
Home-page: https://github.com/gsteixeira/django-except-catcher
Author: Gustavo Selbach Teixeira
Author-email: gsteixei@gmail.com
License: GNU License
Platform: UNKNOWN
Classifier: Environment :: Web Environment
Classifier: Framework :: Django
License-File: LICENSE
